validate_choice_field/__init__.py
validate_choice_field/module.py
validate_choice_field-1.2.1.dist-info/licenses/LICENSE
validate_choice_field-1.2.1.dist-info/METADATA
validate_choice_field-1.2.1.dist-info/WHEEL
validate_choice_field-1.2.1.dist-info/top_level.txt
validate_choice_field-1.2.1.dist-info/RECORD
