Metadata-Version: 2.4
Name: validate_choice_field
Version: 1.2.1
Summary: It is a Python package that allows users to validate a post value against the choices defined in a Django model choice field and returns the corresponding choice data for database storage.
Home-page: https://github.com/gksgassali/validate_choice_field
Author: muhammed gassali
Author-email: gassalirgc@gmail.com
Classifier: Programming Language :: Python :: 3
Classifier: License :: OSI Approved :: MIT License
Classifier: Operating System :: OS Independent
Requires-Python: >=3.6
License-File: LICENSE
Dynamic: author
Dynamic: author-email
Dynamic: classifier
Dynamic: description
Dynamic: description-content-type
Dynamic: home-page
Dynamic: license-file
Dynamic: requires-python
Dynamic: summary
